geodense/__init__.py
geodense/geojson.py
geodense/lib.py
geodense/main.py
geodense/models.py
geodense/types.py
geodense-2.0.2.dist-info/METADATA
geodense-2.0.2.dist-info/WHEEL
geodense-2.0.2.dist-info/entry_points.txt
geodense-2.0.2.dist-info/licenses/LICENSE
geodense-2.0.2.dist-info/RECORD
