Metadata-Version: 2.3
Name: geodense
Version: 2.0.2
Summary: Python library and CLI tool to check density and densify (GeoJSON) geometries using the geodesic (ellipsoidal great-circle) calculation for accurate CRS transformations
Project-URL: repository, https://github.com/GeodetischeInfrastructuur/geodense
License: MIT
License-File: LICENSE
Keywords: CRS,NSGI,coordinate reference system,densify,geodesic,geojson,great-circle
Classifier: Programming Language :: Python :: 3
Classifier: Programming Language :: Python :: 3 :: Only
Classifier: Programming Language :: Python :: 3.10
Requires-Python: >=3.10
Requires-Dist: geojson-pydantic~=1.0
Requires-Dist: pyproj~=3.7.0
Requires-Dist: rich-argparse~=1.3
Requires-Dist: shapely~=2.0.6
